{"resourceNames":[{"name":"Shelter","ID":0},{"name":"Fuel","ID":1},{"name":"Food","ID":2},{"name":"Food Storage","ID":3},{"name":"Materials","ID":4},{"name":"Medicine","ID":5}],"currentCity":{"name":"Vancouver","age":21,"explorationLevel":0.900000095367432,"shelterTier":1,"fuelToShelterConversion":0,"health":0.311040014028549,"foodConsumption":1,"notEnoughFoodHealthDecay":0.800000011920929,"season":0,"isDeadOfWinter":false,"people":[{"ID":0,"infectionLevel":0,"isDead":false,"taskID":1},{"ID":1,"infectionLevel":0,"isDead":false,"taskID":1},{"ID":2,"infectionLevel":0,"isDead":false,"taskID":1}],"buildings":[{"name":"Town Hall","ID":0,"cityName":"Vancouver","status":2,"percentInfected":0,"percentDamaged":0,"percentAssessed":1,"tasks":[{"ID":0,"name":"Idle","buildingName":"Town Hall","maxPeople":1,"numPeople":0,"fullAssessRequirement":1,"taskEnabled":true,"numTurnsToComplete":0,"resourceOutput":null,"resourceInput":null,"taskSlots":[{"taskName":"Idle","taskSlotEnabled":true,"lockedIn":false,"numTurnsPassed":0,"structuralDamage":0,"fungalDamage":0,"personID":null}],"specialTask":"idle"},{"ID":1,"name":"Explore","buildingName":"Town Hall","maxPeople":4,"numPeople":3,"fullAssessRequirement":1,"taskEnabled":true,"numTurnsToComplete":0,"resourceOutput":null,"resourceInput":null,"taskSlots":[{"taskName":"Explore","taskSlotEnabled":true,"lockedIn":false,"numTurnsPassed":0,"structuralDamage":0,"fungalDamage":0,"personID":0},{"taskName":"Explore","taskSlotEnabled":true,"lockedIn":false,"numTurnsPassed":0,"structuralDamage":0,"fungalDamage":0,"personID":2},{"taskName":"Explore","taskSlotEnabled":true,"lockedIn":false,"numTurnsPassed":0,"structuralDamage":0,"fungalDamage":0,"personID":1},{"taskName":"Explore","taskSlotEnabled":true,"lockedIn":false,"numTurnsPassed":0,"structuralDamage":0,"fungalDamage":0,"personID":null}],"specialTask":"explore","exploreAmount":0.100000001490116},{"ID":2,"name":"Assess Building","buildingName":"Town Hall","maxPeople":1,"numPeople":0,"fullAssessRequirement":0,"taskEnabled":false,"numTurnsToComplete":0,"resourceOutput":null,"resourceInput":null,"taskSlots":[{"taskName":"Assess Building","taskSlotEnabled":true,"lockedIn":false,"numTurnsPassed":0,"structuralDamage":0,"fungalDamage":0,"personID":null}],"specialTask":"assess","assessAmount":0.200000002980232}],"position":{"x":0,"y":0}},{"name":"Apartment Building","ID":1,"cityName":"Vancouver","status":1,"percentInfected":0.461044549942017,"percentDamaged":0.5,"percentAssessed":0,"tasks":[{"ID":3,"name":"Assess Building","buildingName":"Apartment Building","maxPeople":1,"numPeople":0,"fullAssessRequirement":0,"taskEnabled":true,"numTurnsToComplete":0,"resourceOutput":null,"resourceInput":null,"taskSlots":[{"taskName":"Assess Building","taskSlotEnabled":true,"lockedIn":false,"numTurnsPassed":0,"structuralDamage":0,"fungalDamage":0,"personID":null}],"specialTask":"assess","assessAmount":0.200000002980232},{"ID":4,"name":"Apartment Super","buildingName":"Apartment Building","maxPeople":1,"numPeople":0,"fullAssessRequirement":0.600000023841858,"taskEnabled":true,"numTurnsToComplete":0,"resourceOutput":{"name":"Shelter","ID":0,"amount":20},"resourceInput":null,"taskSlots":[{"taskName":"Apartment Super","taskSlotEnabled":false,"lockedIn":false,"numTurnsPassed":0,"structuralDamage":1,"fungalDamage":0.922089099884033,"personID":null}]}],"position":{"x":5.59999990463257,"y":-3.09999990463257}},{"name":"Gas Station","ID":2,"cityName":"Vancouver","status":1,"percentInfected":0.345580101013184,"percentDamaged":0.35962575674057,"percentAssessed":0,"tasks":[{"ID":5,"name":"Assess Building","buildingName":"Gas Station","maxPeople":1,"numPeople":0,"fullAssessRequirement":0,"taskEnabled":true,"numTurnsToComplete":0,"resourceOutput":null,"resourceInput":null,"taskSlots":[{"taskName":"Assess Building","taskSlotEnabled":true,"lockedIn":false,"numTurnsPassed":0,"structuralDamage":0,"fungalDamage":0,"personID":null}],"specialTask":"assess","assessAmount":0.200000002980232},{"ID":6,"name":"Fuel Pump","buildingName":"Gas Station","maxPeople":2,"numPeople":0,"fullAssessRequirement":0.699999988079071,"taskEnabled":true,"numTurnsToComplete":0,"resourceOutput":{"name":"Fuel","ID":1,"amount":4},"resourceInput":null,"taskSlots":[{"taskName":"Fuel Pump","taskSlotEnabled":false,"lockedIn":false,"numTurnsPassed":0,"structuralDamage":0.855530619621277,"fungalDamage":0.459793746471405,"personID":null},{"taskName":"Fuel Pump","taskSlotEnabled":false,"lockedIn":false,"numTurnsPassed":0,"structuralDamage":0.582972407341003,"fungalDamage":0.922526717185974,"personID":null}]}],"position":{"x":-5,"y":-1.79999995231628}},{"name":"Library","ID":3,"cityName":"Vancouver","status":1,"percentInfected":0,"percentDamaged":0,"percentAssessed":0,"tasks":[{"ID":7,"name":"Assess Building","buildingName":"Library","maxPeople":1,"numPeople":0,"fullAssessRequirement":0,"taskEnabled":true,"numTurnsToComplete":0,"resourceOutput":null,"resourceInput":null,"taskSlots":[{"taskName":"Assess Building","taskSlotEnabled":true,"lockedIn":false,"numTurnsPassed":0,"structuralDamage":0,"fungalDamage":0,"personID":null}],"specialTask":"assess","assessAmount":0.200000002980232}],"position":{"x":-3.20000004768372,"y":0.300000011920929}},{"name":"Grocery Store","ID":4,"cityName":"Vancouver","status":0,"percentInfected":0.413382411003113,"percentDamaged":0.276560068130493,"percentAssessed":0,"tasks":[{"ID":8,"name":"Assess Building","buildingName":"Grocery Store","maxPeople":1,"numPeople":0,"fullAssessRequirement":0,"taskEnabled":true,"numTurnsToComplete":0,"resourceOutput":null,"resourceInput":null,"taskSlots":[{"taskName":"Assess Building","taskSlotEnabled":true,"lockedIn":false,"numTurnsPassed":0,"structuralDamage":0,"fungalDamage":0,"personID":null}],"specialTask":"assess","assessAmount":0.200000002980232},{"ID":9,"name":"Food Production","buildingName":"Grocery Store","maxPeople":2,"numPeople":0,"fullAssessRequirement":0.400000005960464,"taskEnabled":true,"numTurnsToComplete":0,"resourceOutput":{"name":"Food","ID":2,"amount":10},"resourceInput":null,"taskSlots":[{"taskName":"Food Production","taskSlotEnabled":false,"lockedIn":false,"numTurnsPassed":0,"structuralDamage":0.329513192176819,"fungalDamage":0.515509903430939,"personID":null},{"taskName":"Food Production","taskSlotEnabled":false,"lockedIn":false,"numTurnsPassed":0,"structuralDamage":0.085500031709671,"fungalDamage":0.399473369121552,"personID":null}]},{"ID":10,"name":"Food Storage Management","buildingName":"Grocery Store","maxPeople":1,"numPeople":0,"fullAssessRequirement":0.699999988079071,"taskEnabled":true,"numTurnsToComplete":0,"resourceOutput":{"name":"Food Storage","ID":3,"amount":20},"resourceInput":null,"taskSlots":[{"taskName":"Food Storage Management","taskSlotEnabled":false,"lockedIn":false,"numTurnsPassed":0,"structuralDamage":0.622173607349396,"fungalDamage":0.782655596733093,"personID":null}]}],"position":{"x":1.60000002384186,"y":-2.79999995231628}}],"resources":[{"name":"Food","ID":2,"amount":49},{"name":"Fuel","ID":1,"amount":0},{"name":"Materials","ID":4,"amount":0},{"name":"Medicine","ID":5,"amount":0},{"name":"Shelter","ID":0,"amount":0}],"linked_cities":["Iqaluit","Ottawa"]},"currentDate":{"day":22,"month":4,"year":2017},"turnDurationOfCity":52,"durationOfTurn":7,"currentTurnNumber":3,"availableCities":["Iqaluit","Montreal","Ottawa","Toronto","Vancouver"]}