[
  {
    "id": 0,
    "priority": 1,
    "turnsToActivate": 1,
    "promptText": "Oh shit, you found some tacos!\nYou got 50 food.",
    "activationCondition": "exploring",
    "resources": [
      {
        "type": "Food",
        "value": 50
      }
    ]
  },
  {
    "id": 1,
    "priority": 1,
    "turnsToActivate": 7,
    "promptText": "A weekly shipment of food has arrived!",
    "activationCondition": true,
    "resources": [
      {
        "type": "Food",
        "value": 1000
      }
    ],
    "nextEvent": {
      "id": 1,
      "type": "modify"
    }
  }
]